nbv.py
nbv-0.0.5.dist-info/entry_points.txt
nbv-0.0.5.dist-info/licenses/LICENSE
nbv-0.0.5.dist-info/WHEEL
nbv-0.0.5.dist-info/METADATA
nbv-0.0.5.dist-info/RECORD
