Metadata-Version: 2.4
Name: nbv
Version: 0.0.5
Summary: Read-only viewing of Jupyter notebooks in the web browser.
Requires-Python: >=3.7
License-File: LICENSE
Requires-Dist: rich
Requires-Dist: typer
Requires-Dist: ipython ; extra == "complete"
Requires-Dist: nbconvert ~=7.0 ; extra == "complete"
Provides-Extra: complete
